[
  {
    "name": null,
    "methods": [
      "HEAD",
      "GET"
    ],
    "paramNames": [],
    "path": "/",
    "regexp": "/^(?:\\/(?=$))?$/",
    "stack": [
      "wrappedController"
    ]
  },
  {
    "name": null,
    "methods": [
      "POST"
    ],
    "paramNames": [],
    "path": "/mock/api/article/list",
    "regexp": "/^\\/mock\\/api\\/article\\/list(?:\\/(?=$))?$/",
    "stack": [
      "wrappedController"
    ]
  },
  {
    "name": null,
    "methods": [
      "POST"
    ],
    "paramNames": [],
    "path": "/mock/api/article/add",
    "regexp": "/^\\/mock\\/api\\/article\\/add(?:\\/(?=$))?$/",
    "stack": [
      "wrappedController"
    ]
  },
  {
    "name": null,
    "methods": [
      "HEAD",
      "GET"
    ],
    "paramNames": [
      {
        "name": "id",
        "prefix": "/",
        "delimiter": "/",
        "optional": false,
        "repeat": false,
        "partial": false,
        "asterisk": false,
        "pattern": "[^\\/]+?"
      }
    ],
    "path": "/mock/api/article/del/:id",
    "regexp": "/^\\/mock\\/api\\/article\\/del\\/((?:[^\\/]+?))(?:\\/(?=$))?$/",
    "stack": [
      "wrappedController"
    ]
  },
  {
    "name": null,
    "methods": [
      "HEAD",
      "GET"
    ],
    "paramNames": [
      {
        "name": "id",
        "prefix": "/",
        "delimiter": "/",
        "optional": false,
        "repeat": false,
        "partial": false,
        "asterisk": false,
        "pattern": "[^\\/]+?"
      }
    ],
    "path": "/mock/api/article/:id",
    "regexp": "/^\\/mock\\/api\\/article\\/((?:[^\\/]+?))(?:\\/(?=$))?$/",
    "stack": [
      "wrappedController"
    ]
  },
  {
    "name": null,
    "methods": [
      "POST"
    ],
    "paramNames": [],
    "path": "/mock/api/url/swagger",
    "regexp": "/^\\/mock\\/api\\/url\\/swagger(?:\\/(?=$))?$/",
    "stack": [
      "wrappedController"
    ]
  },
  {
    "name": null,
    "methods": [
      "POST"
    ],
    "paramNames": [],
    "path": "/mock/api/url/delete",
    "regexp": "/^\\/mock\\/api\\/url\\/delete(?:\\/(?=$))?$/",
    "stack": [
      "wrappedController"
    ]
  },
  {
    "name": null,
    "methods": [
      "POST"
    ],
    "paramNames": [],
    "path": "/mock/api/url/batch/delete",
    "regexp": "/^\\/mock\\/api\\/url\\/batch\\/delete(?:\\/(?=$))?$/",
    "stack": [
      "wrappedController"
    ]
  },
  {
    "name": null,
    "methods": [
      "POST"
    ],
    "paramNames": [],
    "path": "/mock/api/url/request/target/switch",
    "regexp": "/^\\/mock\\/api\\/url\\/request\\/target\\/switch(?:\\/(?=$))?$/",
    "stack": [
      "wrappedController"
    ]
  },
  {
    "name": null,
    "methods": [
      "HEAD",
      "GET"
    ],
    "paramNames": [],
    "path": "/mock/api/url/list",
    "regexp": "/^\\/mock\\/api\\/url\\/list(?:\\/(?=$))?$/",
    "stack": [
      "wrappedController"
    ]
  },
  {
    "name": null,
    "methods": [
      "POST"
    ],
    "paramNames": [],
    "path": "/mock/api/url/mock/data",
    "regexp": "/^\\/mock\\/api\\/url\\/mock\\/data(?:\\/(?=$))?$/",
    "stack": [
      "wrappedController"
    ]
  },
  {
    "name": null,
    "methods": [
      "HEAD",
      "GET"
    ],
    "paramNames": [],
    "path": "/mock/api/url/response/list",
    "regexp": "/^\\/mock\\/api\\/url\\/response\\/list(?:\\/(?=$))?$/",
    "stack": [
      "wrappedController"
    ]
  },
  {
    "name": null,
    "methods": [
      "HEAD",
      "GET"
    ],
    "paramNames": [],
    "path": "/mock/api/url/response/by/params",
    "regexp": "/^\\/mock\\/api\\/url\\/response\\/by\\/params(?:\\/(?=$))?$/",
    "stack": [
      "wrappedController"
    ]
  },
  {
    "name": null,
    "methods": [
      "POST"
    ],
    "paramNames": [],
    "path": "/mock/api/url/response/edit",
    "regexp": "/^\\/mock\\/api\\/url\\/response\\/edit(?:\\/(?=$))?$/",
    "stack": [
      "wrappedController"
    ]
  },
  {
    "name": null,
    "methods": [
      "HEAD",
      "GET"
    ],
    "paramNames": [],
    "path": "/mock/api/system/list",
    "regexp": "/^\\/mock\\/api\\/system\\/list(?:\\/(?=$))?$/",
    "stack": [
      "wrappedController"
    ]
  },
  {
    "name": null,
    "methods": [
      "POST"
    ],
    "paramNames": [],
    "path": "/mock/api/system/add",
    "regexp": "/^\\/mock\\/api\\/system\\/add(?:\\/(?=$))?$/",
    "stack": [
      "wrappedController"
    ]
  },
  {
    "name": null,
    "methods": [
      "POST"
    ],
    "paramNames": [],
    "path": "/mock/api/system/delete",
    "regexp": "/^\\/mock\\/api\\/system\\/delete(?:\\/(?=$))?$/",
    "stack": [
      "wrappedController"
    ]
  },
  {
    "name": null,
    "methods": [
      "HEAD",
      "GET"
    ],
    "paramNames": [
      {
        "name": 0,
        "prefix": "",
        "delimiter": "/",
        "optional": true,
        "repeat": false,
        "partial": false,
        "asterisk": false,
        "pattern": "\\/.+"
      }
    ],
    "path": "/mock(/.+)?",
    "regexp": "/^\\/mock(?:((?:\\/.+)))?(?:\\/(?=$))?$/",
    "stack": [
      "wrappedController"
    ]
  },
  {
    "name": null,
    "methods": [
      "HEAD",
      "GET"
    ],
    "paramNames": [],
    "path": {
      "keys": []
    },
    "regexp": "/[a-z]+/",
    "stack": [
      "wrappedController"
    ]
  },
  {
    "name": null,
    "methods": [
      "POST"
    ],
    "paramNames": [],
    "path": {
      "keys": []
    },
    "regexp": "/[a-z]+/",
    "stack": [
      "wrappedController"
    ]
  }
]